textnormaliser/__init__.py
textnormaliser-1.0.0.dist-info/LICENSE
textnormaliser-1.0.0.dist-info/METADATA
textnormaliser-1.0.0.dist-info/WHEEL
textnormaliser-1.0.0.dist-info/entry_points.txt
textnormaliser-1.0.0.dist-info/top_level.txt
textnormaliser-1.0.0.dist-info/RECORD
