Metadata-Version: 2.1
Name: textnormaliser
Version: 1.0.0
Summary: A python package that runs a series of operations over text to decorate a corpus
Home-page: https://github.com/dust10141/text-normaliser
Author: Will Sackfield
Author-email: will.sackfield@gmail.com
License: MIT
Platform: UNKNOWN
Requires-Dist: langdetect (==1.0.7)
Requires-Dist: tqdm (==4.28.1)
Requires-Dist: nltk (==3.4)
Requires-Dist: spacy (==2.0.16)
